Obito/__init__.py
Obito/downloader.py
Obito/get_filesize.py
obito-0.1.0.dist-info/entry_points.txt
obito-0.1.0.dist-info/WHEEL
obito-0.1.0.dist-info/METADATA
obito-0.1.0.dist-info/RECORD
