Metadata-Version: 2.1
Name: obito
Version: 0.1.0
Summary: A URL file downloader that can download multiple files concurrently over internet.
Home-page: https://github.com/777advait/Obito
License: MIT
Author: 777advait
Requires-Python: >=3.7,<4.0
Classifier: License :: OSI Approved :: MIT License
Classifier: Programming Language :: Python :: 3
Classifier: Programming Language :: Python :: 3.10
Classifier: Programming Language :: Python :: 3.7
Classifier: Programming Language :: Python :: 3.8
Classifier: Programming Language :: Python :: 3.9
Requires-Dist: rich (>=12.4.4,<13.0.0)
Requires-Dist: typer (>=0.4.1,<0.5.0)
Project-URL: Bug Tracker, https://github.com/777advait/Obito/issues
Project-URL: Repository, https://github.com/777advait/Obito
